polychromatic_effects_generator/__init__.py
polychromatic_effects_generator/__main__.py
polychromatic_effects_generator/colors.py
polychromatic_effects_generator/effect.py
polychromatic_effects_generator/layers/base.py
polychromatic_effects_generator/layers/breathing.py
polychromatic_effects_generator/layers/spectrum.py
polychromatic_effects_generator/layers/static.py
polychromatic_effects_generator/layers/wave.py
polychromatic_effects_generator/layers/wheel.py
polychromatic_effects_generator/math/lerp.py
polychromatic_effects_generator/math/vector.py
polychromatic_effects_generator-1.0.0.dist-info/METADATA
polychromatic_effects_generator-1.0.0.dist-info/WHEEL
polychromatic_effects_generator-1.0.0.dist-info/entry_points.txt
polychromatic_effects_generator-1.0.0.dist-info/licenses/LICENSE
polychromatic_effects_generator-1.0.0.dist-info/RECORD
