Metadata-Version: 2.4
Name: polychromatic_effects_generator
Version: 1.0.0
Summary: Tool for generating advanced RGB effects for Polychromatic
Project-URL: Repository, https://github.com/hashadex/polychromatic-effects-generator
Author-email: Artem Denisov <hashadex@outlook.com>
License-Expression: MIT
License-File: LICENSE
Keywords: polychromatic,razer,rgb
Classifier: Development Status :: 4 - Beta
Classifier: Intended Audience :: End Users/Desktop
Classifier: License :: OSI Approved :: MIT License
Classifier: Operating System :: OS Independent
Classifier: Programming Language :: Python :: 3.13
Requires-Python: >=3.13
Requires-Dist: pyyaml~=6.0.2
